fast_writer/__init__.py
fast_writer/converter.py
fast_writer/main.py
fast_writer/merger.py
fast_writer/preview.py
fast_writer/utils.py
fast_writer-1.0.3.dist-info/licenses/LICENSE
fast_writer-1.0.3.dist-info/METADATA
fast_writer-1.0.3.dist-info/WHEEL
fast_writer-1.0.3.dist-info/entry_points.txt
fast_writer-1.0.3.dist-info/top_level.txt
fast_writer-1.0.3.dist-info/RECORD
