Metadata-Version: 2.4
Name: fast-writer
Version: 1.0.3
Summary: CLI Tools for writing data
Author-email: Jinwook Chang <tranquil_morning@icloud.com>
Project-URL: Homepage, https://github.com/jinwook-chang/fast-writer
Project-URL: Repository, https://github.com/jinwook-chang/fast-writer
Project-URL: Bug Tracker, https://github.com/jinwook-chang/fast-writer/issues
Keywords: polars,cli,data processing,file conversion,file merge,fastwriter
Classifier: Development Status :: 3 - Alpha
Classifier: Programming Language :: Python :: 3
Classifier: Programming Language :: Python :: 3.8
Classifier: Programming Language :: Python :: 3.9
Classifier: Programming Language :: Python :: 3.10
Classifier: Programming Language :: Python :: 3.11
Classifier: Programming Language :: Python :: 3.12
Classifier: License :: OSI Approved :: MIT License
Classifier: Operating System :: OS Independent
Classifier: Topic :: Utilities
Classifier: Intended Audience :: Developers
Classifier: Intended Audience :: End Users/Desktop
Classifier: Typing :: Typed
Requires-Python: >=3.8
License-File: LICENSE
Requires-Dist: polars>=1.0.0
Requires-Dist: typer[all]>=0.9.0
Requires-Dist: openpyxl>=3.0.0
Requires-Dist: pandas>=2.0.0
Requires-Dist: numpy~=2.2.0
Requires-Dist: xlwings>=0.30.0
Dynamic: license-file
